eth_keyfile/__init__.py
eth_keyfile/keyfile.py
eth_keyfile/py.typed
eth_keyfile-0.8.0.dist-info/LICENSE
eth_keyfile-0.8.0.dist-info/METADATA
eth_keyfile-0.8.0.dist-info/WHEEL
eth_keyfile-0.8.0.dist-info/top_level.txt
eth_keyfile-0.8.0.dist-info/RECORD
