Metadata-Version: 2.1
Name: eth-keyfile
Version: 0.8.0
Summary: eth-keyfile: A library for handling the encrypted keyfiles used to store ethereum private keys
Home-page: https://github.com/ethereum/eth-keyfile
Author: The Ethereum Foundation
Author-email: snakecharmers@ethereum.org
License: MIT
Keywords: ethereum
Classifier: Development Status :: 2 - Pre-Alpha
Classifier: Intended Audience :: Developers
Classifier: License :: OSI Approved :: MIT License
Classifier: Natural Language :: English
Classifier: Programming Language :: Python :: 3
Classifier: Programming Language :: Python :: 3.8
Classifier: Programming Language :: Python :: 3.9
Classifier: Programming Language :: Python :: 3.10
Classifier: Programming Language :: Python :: 3.11
Requires-Python: >=3.8, <4
License-File: LICENSE
Requires-Dist: eth-utils>=2
Requires-Dist: eth-keys>=0.4.0
Requires-Dist: pycryptodome<4,>=3.6.6
Provides-Extra: dev
Requires-Dist: build>=0.9.0; extra == "dev"
Requires-Dist: bumpversion>=0.5.3; extra == "dev"
Requires-Dist: ipython; extra == "dev"
Requires-Dist: pre-commit>=3.4.0; extra == "dev"
Requires-Dist: tox>=4.0.0; extra == "dev"
Requires-Dist: twine; extra == "dev"
Requires-Dist: wheel; extra == "dev"
Requires-Dist: towncrier<22,>=21; extra == "dev"
Requires-Dist: pytest>=7.0.0; extra == "dev"
Requires-Dist: pytest-xdist>=2.4.0; extra == "dev"
Provides-Extra: docs
Requires-Dist: towncrier<22,>=21; extra == "docs"
Provides-Extra: test
Requires-Dist: pytest>=7.0.0; extra == "test"
Requires-Dist: pytest-xdist>=2.4.0; extra == "test"
